pokepastes_scraper/__init__.py
pokepastes_scraper-0.2.2.dist-info/LICENSE
pokepastes_scraper-0.2.2.dist-info/METADATA
pokepastes_scraper-0.2.2.dist-info/WHEEL
pokepastes_scraper-0.2.2.dist-info/top_level.txt
pokepastes_scraper-0.2.2.dist-info/RECORD
