Metadata-Version: 2.1
Name: pokepastes-scraper
Version: 0.2.2
Summary: Extracts Pokémon team information from a https://pokepast.es/ URL to a JSON-serializable Python object.
Author-email: MyApaulogies <myapaulogies@tuta.io>
License: MIT License
Project-URL: Homepage, https://github.com/MyApaulogies/pokepastes-scraper
Classifier: Programming Language :: Python :: 3
Classifier: License :: OSI Approved :: MIT License
Classifier: Operating System :: OS Independent
Requires-Python: >=3.10
License-File: LICENSE
Requires-Dist: requests
Requires-Dist: beautifulsoup4
